<?xml version="1.0" encoding="UTF-8"?>
<!-- Copyright 2001-2019 Opta Sportsdata Ltd. All rights reserved. -->
<!-- PRODUCTION HEADER
     produced on:        valde-jobq-a03.nexus.opta.net
     production time:    20190102T170346,878Z
     production module:  Opta::Feed::XML::Soccer::F27
-->
<SoccerFeed act_minute="93" act_period="2" act_second="25" away_team_id="1450" away_team_name="Getafe" competition_id="23" competition_name="Spanish La Liga" game_date="2018-12-21 18:30:00" game_id="1009482" home_team_id="2893" home_team_name="Girona" season_id="2018" season_name="Season 2018/2019" team_id="2893" team_name="Girona">
  <Player cross_lost="0" cross_success="0" jersey_num="19" pass_lost="5" pass_success="5" player_id="104448" player_name="Anthony Lozano" position="Substitute" position_id="5" sub_on="72" x="50.72" y="75.69">
    <Player player_id="469274" player_name="Valery Fernández">2</Player>
    <Player player_id="63119" player_name="Juanpe">1</Player>
    <Player player_id="131411" player_name="Pere Pons">1</Player>
    <Player player_id="49464" player_name="Cristhian Stuani">1</Player>
  </Player>
  <Player cross_lost="0" cross_success="0" jersey_num="34" pass_lost="5" pass_success="5" player_id="469274" player_name="Valery Fernández" position="Substitute" position_id="5" sub_on="72" x="51.07" y="85.94">
    <Player player_id="104448" player_name="Anthony Lozano">1</Player>
    <Player player_id="63119" player_name="Juanpe">1</Player>
    <Player player_id="131411" player_name="Pere Pons">1</Player>
    <Player player_id="139472" player_name="Álex Granell">1</Player>
    <Player player_id="63904" player_name="Borja García">1</Player>
  </Player>
  <Player cross_lost="0" cross_success="0" jersey_num="2" pass_lost="6" pass_success="59" player_id="55317" player_name="Bernardo Espinosa" position="Defender" position_id="2" x="34.69" y="44.44">
    <Player player_id="104448" player_name="Anthony Lozano">1</Player>
    <Player player_id="469274" player_name="Valery Fernández">1</Player>
    <Player player_id="178871" player_name="Aleix García">5</Player>
    <Player player_id="120026" player_name="Yassine Bounou">3</Player>
    <Player player_id="63119" player_name="Juanpe">22</Player>
    <Player player_id="139472" player_name="Álex Granell">7</Player>
    <Player player_id="131411" player_name="Pere Pons">4</Player>
    <Player player_id="88550" player_name="Portu">1</Player>
    <Player player_id="63904" player_name="Borja García">5</Player>
    <Player player_id="80077" player_name="Jonás Ramalho">10</Player>
  </Player>
  <Player cross_lost="3" cross_success="0" jersey_num="29" pass_lost="11" pass_success="24" player_id="441164" player_name="Pedro Porro" position="Midfielder" position_id="3" sub_off="72" x="53.02" y="11.64">
    <Player player_id="55317" player_name="Bernardo Espinosa">2</Player>
    <Player player_id="178871" player_name="Aleix García">3</Player>
    <Player player_id="131411" player_name="Pere Pons">2</Player>
    <Player player_id="88550" player_name="Portu">3</Player>
    <Player player_id="80077" player_name="Jonás Ramalho">13</Player>
    <Player player_id="49464" player_name="Cristhian Stuani">1</Player>
  </Player>
  <Player cross_lost="0" cross_success="1" jersey_num="23" pass_lost="8" pass_success="44" player_id="178871" player_name="Aleix García" position="Midfielder" position_id="3" sub_off="72" x="47.33" y="37.36">
    <Player player_id="55317" player_name="Bernardo Espinosa">3</Player>
    <Player player_id="120026" player_name="Yassine Bounou">2</Player>
    <Player player_id="131411" player_name="Pere Pons">3</Player>
    <Player player_id="139472" player_name="Álex Granell">5</Player>
    <Player player_id="63904" player_name="Borja García">7</Player>
    <Player player_id="441164" player_name="Pedro Porro">13</Player>
    <Player player_id="63119" player_name="Juanpe">3</Player>
    <Player player_id="88550" player_name="Portu">2</Player>
    <Player cross="1" player_id="80077" player_name="Jonás Ramalho">3</Player>
    <Player player_id="49464" player_name="Cristhian Stuani">3</Player>
  </Player>
  <Player cross_lost="0" cross_success="0" jersey_num="13" pass_lost="11" pass_success="26" player_id="120026" player_name="Yassine Bounou" position="Goalkeeper" position_id="1" x="9.89" y="51.97">
    <Player player_id="55317" player_name="Bernardo Espinosa">2</Player>
    <Player player_id="178871" player_name="Aleix García">1</Player>
    <Player player_id="63119" player_name="Juanpe">9</Player>
    <Player player_id="139472" player_name="Álex Granell">4</Player>
    <Player player_id="131411" player_name="Pere Pons">2</Player>
    <Player player_id="63904" player_name="Borja García">1</Player>
    <Player player_id="80077" player_name="Jonás Ramalho">7</Player>
  </Player>
  <Player cross_lost="0" cross_success="0" jersey_num="15" pass_lost="11" pass_success="68" player_id="63119" player_name="Juanpe" position="Defender" position_id="2" x="32.66" y="75.43">
    <Player player_id="469274" player_name="Valery Fernández">2</Player>
    <Player player_id="104448" player_name="Anthony Lozano">3</Player>
    <Player player_id="55317" player_name="Bernardo Espinosa">11</Player>
    <Player player_id="441164" player_name="Pedro Porro">1</Player>
    <Player player_id="178871" player_name="Aleix García">3</Player>
    <Player player_id="120026" player_name="Yassine Bounou">12</Player>
    <Player player_id="131411" player_name="Pere Pons">3</Player>
    <Player player_id="139472" player_name="Álex Granell">16</Player>
    <Player player_id="63904" player_name="Borja García">15</Player>
    <Player player_id="80077" player_name="Jonás Ramalho">1</Player>
    <Player player_id="49464" player_name="Cristhian Stuani">1</Player>
  </Player>
  <Player cross_lost="0" cross_success="0" jersey_num="8" pass_lost="13" pass_success="47" player_id="131411" player_name="Pere Pons" position="Midfielder" position_id="3" x="49.27" y="51.62">
    <Player player_id="104448" player_name="Anthony Lozano">1</Player>
    <Player player_id="55317" player_name="Bernardo Espinosa">9</Player>
    <Player player_id="441164" player_name="Pedro Porro">3</Player>
    <Player player_id="178871" player_name="Aleix García">5</Player>
    <Player player_id="63119" player_name="Juanpe">3</Player>
    <Player player_id="139472" player_name="Álex Granell">9</Player>
    <Player player_id="88550" player_name="Portu">3</Player>
    <Player player_id="63904" player_name="Borja García">6</Player>
    <Player player_id="80077" player_name="Jonás Ramalho">6</Player>
    <Player player_id="49464" player_name="Cristhian Stuani">2</Player>
  </Player>
  <Player cross_lost="7" cross_success="4" jersey_num="6" pass_lost="18" pass_success="58" player_id="139472" player_name="Álex Granell" position="Midfielder" position_id="3" x="47.01" y="73.56">
    <Player player_id="469274" player_name="Valery Fernández">2</Player>
    <Player cross="2" player_id="55317" player_name="Bernardo Espinosa">3</Player>
    <Player player_id="178871" player_name="Aleix García">4</Player>
    <Player player_id="120026" player_name="Yassine Bounou">2</Player>
    <Player player_id="131411" player_name="Pere Pons">6</Player>
    <Player player_id="63904" player_name="Borja García">22</Player>
    <Player player_id="104448" player_name="Anthony Lozano">1</Player>
    <Player player_id="441164" player_name="Pedro Porro">1</Player>
    <Player player_id="63119" player_name="Juanpe">9</Player>
    <Player cross="1" player_id="88550" player_name="Portu">3</Player>
    <Player player_id="80077" player_name="Jonás Ramalho">1</Player>
    <Player cross="1" player_id="49464" player_name="Cristhian Stuani">4</Player>
  </Player>
  <Player cross_lost="1" cross_success="0" jersey_num="9" pass_lost="5" pass_success="15" player_id="88550" player_name="Portu" position="Forward" position_id="4" x="64.07" y="24.03">
    <Player player_id="441164" player_name="Pedro Porro">4</Player>
    <Player player_id="178871" player_name="Aleix García">1</Player>
    <Player player_id="139472" player_name="Álex Granell">4</Player>
    <Player player_id="131411" player_name="Pere Pons">3</Player>
    <Player player_id="63904" player_name="Borja García">3</Player>
  </Player>
  <Player cross_lost="0" cross_success="0" jersey_num="10" pass_lost="9" pass_success="61" player_id="63904" player_name="Borja García" position="Forward" position_id="4" x="49.56" y="71.97">
    <Player player_id="469274" player_name="Valery Fernández">1</Player>
    <Player player_id="104448" player_name="Anthony Lozano">3</Player>
    <Player player_id="55317" player_name="Bernardo Espinosa">6</Player>
    <Player player_id="178871" player_name="Aleix García">5</Player>
    <Player player_id="441164" player_name="Pedro Porro">3</Player>
    <Player player_id="63119" player_name="Juanpe">11</Player>
    <Player player_id="131411" player_name="Pere Pons">14</Player>
    <Player player_id="139472" player_name="Álex Granell">13</Player>
    <Player player_id="88550" player_name="Portu">3</Player>
    <Player player_id="49464" player_name="Cristhian Stuani">2</Player>
  </Player>
  <Player cross_lost="1" cross_success="0" jersey_num="4" pass_lost="5" pass_success="47" player_id="80077" player_name="Jonás Ramalho" position="Defender" position_id="2" x="38.08" y="18.54">
    <Player player_id="55317" player_name="Bernardo Espinosa">12</Player>
    <Player player_id="441164" player_name="Pedro Porro">8</Player>
    <Player player_id="178871" player_name="Aleix García">5</Player>
    <Player player_id="120026" player_name="Yassine Bounou">7</Player>
    <Player player_id="63119" player_name="Juanpe">2</Player>
    <Player player_id="139472" player_name="Álex Granell">4</Player>
    <Player player_id="131411" player_name="Pere Pons">2</Player>
    <Player player_id="88550" player_name="Portu">5</Player>
    <Player player_id="49464" player_name="Cristhian Stuani">2</Player>
  </Player>
  <Player cross_lost="0" cross_success="0" jersey_num="7" pass_lost="8" pass_success="11" player_id="49464" player_name="Cristhian Stuani" position="Forward" position_id="4" x="66.66" y="47.37">
    <Player player_id="55317" player_name="Bernardo Espinosa">1</Player>
    <Player player_id="178871" player_name="Aleix García">2</Player>
    <Player player_id="131411" player_name="Pere Pons">5</Player>
    <Player player_id="88550" player_name="Portu">2</Player>
    <Player player_id="63904" player_name="Borja García">1</Player>
  </Player>
</SoccerFeed>