<?xml version="1.0" encoding="UTF-8"?>
<!-- Copyright 2001-2018 Opta Sportsdata Ltd. All rights reserved. -->
<!-- PRODUCTION HEADER
     produced on:        valde-jobq-a04.nexus.opta.net
     production time:    20181218T164042,361Z
     production module:  Opta::Feed::XML::Soccer::F27
-->
<SoccerFeed act_minute="93" act_period="2" act_second="7" away_team_id="174" away_team_name="Athletic Club" competition_id="23" competition_name="Spanish La Liga" game_date="2018-12-17 20:00:00" game_id="1009466" home_team_id="173" home_team_name="Alavés" season_id="2018" season_name="Season 2018/2019" team_id="173" team_name="Alavés">
  <Player cross_lost="0" cross_success="0" jersey_num="19" pass_lost="14" pass_success="22" player_id="55378" player_name="Manu García" position="Midfielder" position_id="3" x="44.16" y="52.03">
    <Player player_id="163817" player_name="Burgui">1</Player>
    <Player player_id="84471" player_name="Ibai Gómez">1</Player>
    <Player player_id="92190" player_name="Jony">1</Player>
    <Player player_id="49370" player_name="Víctor Laguardia">4</Player>
    <Player player_id="168287" player_name="Jonathan Calleri">1</Player>
    <Player player_id="112994" player_name="Rubén Sobrino">2</Player>
    <Player player_id="90728" player_name="Ximo Navarro">1</Player>
    <Player player_id="155335" player_name="Guillermo Maripán">3</Player>
    <Player player_id="126119" player_name="Rubén Duarte">2</Player>
    <Player player_id="83091" player_name="Borja Bastón">1</Player>
    <Player player_id="80956" player_name="Tomás Pina">5</Player>
  </Player>
  <Player cross_lost="1" cross_success="1" jersey_num="7" pass_lost="2" pass_success="8" player_id="112994" player_name="Rubén Sobrino" position="Substitute" position_id="5" sub_on="45" x="55.16" y="45.72">
    <Player player_id="126119" player_name="Rubén Duarte">2</Player>
    <Player cross="1" player_id="83091" player_name="Borja Bastón">0</Player>
    <Player player_id="92190" player_name="Jony">1</Player>
    <Player player_id="80956" player_name="Tomás Pina">5</Player>
  </Player>
  <Player cross_lost="3" cross_success="0" jersey_num="12" pass_lost="17" pass_success="13" player_id="168287" player_name="Jonathan Calleri" position="Forward" position_id="4" x="60.52" y="51.32">
    <Player player_id="112994" player_name="Rubén Sobrino">3</Player>
    <Player player_id="163817" player_name="Burgui">1</Player>
    <Player player_id="82970" player_name="John Guidetti">3</Player>
    <Player player_id="84471" player_name="Ibai Gómez">2</Player>
    <Player player_id="92190" player_name="Jony">2</Player>
    <Player player_id="80956" player_name="Tomás Pina">2</Player>
  </Player>
  <Player cross_lost="0" cross_success="0" jersey_num="14" pass_lost="0" pass_success="4" player_id="163817" player_name="Burgui" position="Substitute" position_id="5" sub_on="85" x="71.77" y="81.80">
    <Player player_id="126119" player_name="Rubén Duarte">3</Player>
    <Player player_id="168287" player_name="Jonathan Calleri">1</Player>
  </Player>
  <Player cross_lost="0" cross_success="0" jersey_num="10" pass_lost="5" pass_success="5" player_id="82970" player_name="John Guidetti" position="Forward" position_id="4" sub_off="45" x="69.79" y="56.53">
    <Player player_id="84471" player_name="Ibai Gómez">1</Player>
    <Player player_id="92190" player_name="Jony">4</Player>
  </Player>
  <Player cross_lost="0" cross_success="0" jersey_num="1" pass_lost="16" pass_success="24" player_id="91406" player_name="Fernando Pacheco" position="Goalkeeper" position_id="1" x="11.89" y="50.32">
    <Player player_id="55378" player_name="Manu García">2</Player>
    <Player player_id="168287" player_name="Jonathan Calleri">9</Player>
    <Player player_id="90728" player_name="Ximo Navarro">1</Player>
    <Player player_id="155335" player_name="Guillermo Maripán">7</Player>
    <Player player_id="49370" player_name="Víctor Laguardia">5</Player>
  </Player>
  <Player cross_lost="2" cross_success="2" jersey_num="15" pass_lost="6" pass_success="17" player_id="90728" player_name="Ximo Navarro" position="Defender" position_id="2" x="36.64" y="17.33">
    <Player player_id="55378" player_name="Manu García">1</Player>
    <Player cross="2" player_id="168287" player_name="Jonathan Calleri">2</Player>
    <Player player_id="91406" player_name="Fernando Pacheco">1</Player>
    <Player player_id="126119" player_name="Rubén Duarte">3</Player>
    <Player player_id="155335" player_name="Guillermo Maripán">2</Player>
    <Player player_id="84471" player_name="Ibai Gómez">4</Player>
    <Player player_id="80956" player_name="Tomás Pina">1</Player>
    <Player player_id="49370" player_name="Víctor Laguardia">3</Player>
  </Player>
  <Player cross_lost="2" cross_success="2" jersey_num="11" pass_lost="6" pass_success="12" player_id="84471" player_name="Ibai Gómez" position="Midfielder" position_id="3" sub_off="73" x="50.35" y="23.78">
    <Player cross="1" player_id="55378" player_name="Manu García">4</Player>
    <Player player_id="92190" player_name="Jony">1</Player>
    <Player player_id="49370" player_name="Víctor Laguardia">3</Player>
    <Player cross="1" player_id="168287" player_name="Jonathan Calleri">0</Player>
    <Player player_id="112994" player_name="Rubén Sobrino">1</Player>
    <Player player_id="82970" player_name="John Guidetti">1</Player>
    <Player player_id="90728" player_name="Ximo Navarro">1</Player>
    <Player player_id="155335" player_name="Guillermo Maripán">1</Player>
  </Player>
  <Player cross_lost="2" cross_success="0" jersey_num="3" pass_lost="10" pass_success="25" player_id="126119" player_name="Rubén Duarte" position="Defender" position_id="2" x="46.58" y="78.59">
    <Player player_id="112994" player_name="Rubén Sobrino">3</Player>
    <Player player_id="82970" player_name="John Guidetti">2</Player>
    <Player player_id="91406" player_name="Fernando Pacheco">1</Player>
    <Player player_id="90728" player_name="Ximo Navarro">2</Player>
    <Player player_id="155335" player_name="Guillermo Maripán">2</Player>
    <Player player_id="83091" player_name="Borja Bastón">2</Player>
    <Player player_id="92190" player_name="Jony">9</Player>
    <Player player_id="80956" player_name="Tomás Pina">4</Player>
  </Player>
  <Player cross_lost="0" cross_success="0" jersey_num="6" pass_lost="12" pass_success="28" player_id="155335" player_name="Guillermo Maripán" position="Defender" position_id="2" x="30.28" y="65.85">
    <Player player_id="55378" player_name="Manu García">6</Player>
    <Player player_id="168287" player_name="Jonathan Calleri">1</Player>
    <Player player_id="91406" player_name="Fernando Pacheco">3</Player>
    <Player player_id="90728" player_name="Ximo Navarro">2</Player>
    <Player player_id="84471" player_name="Ibai Gómez">1</Player>
    <Player player_id="126119" player_name="Rubén Duarte">7</Player>
    <Player player_id="92190" player_name="Jony">2</Player>
    <Player player_id="49370" player_name="Víctor Laguardia">4</Player>
    <Player player_id="80956" player_name="Tomás Pina">2</Player>
  </Player>
  <Player cross_lost="0" cross_success="0" jersey_num="18" pass_lost="2" pass_success="6" player_id="83091" player_name="Borja Bastón" position="Substitute" position_id="5" sub_on="73" x="63.66" y="64.22">
    <Player player_id="55378" player_name="Manu García">1</Player>
    <Player player_id="168287" player_name="Jonathan Calleri">3</Player>
    <Player player_id="126119" player_name="Rubén Duarte">1</Player>
    <Player player_id="92190" player_name="Jony">1</Player>
  </Player>
  <Player cross_lost="8" cross_success="2" jersey_num="23" pass_lost="9" pass_success="18" player_id="92190" player_name="Jony" position="Midfielder" position_id="3" sub_off="85" x="61.52" y="78.25">
    <Player player_id="84471" player_name="Ibai Gómez">2</Player>
    <Player player_id="49370" player_name="Víctor Laguardia">1</Player>
    <Player cross="2" player_id="168287" player_name="Jonathan Calleri">1</Player>
    <Player player_id="112994" player_name="Rubén Sobrino">2</Player>
    <Player player_id="82970" player_name="John Guidetti">1</Player>
    <Player player_id="90728" player_name="Ximo Navarro">1</Player>
    <Player player_id="126119" player_name="Rubén Duarte">5</Player>
    <Player player_id="155335" player_name="Guillermo Maripán">2</Player>
    <Player player_id="83091" player_name="Borja Bastón">1</Player>
    <Player player_id="80956" player_name="Tomás Pina">2</Player>
  </Player>
  <Player cross_lost="0" cross_success="0" jersey_num="8" pass_lost="9" pass_success="30" player_id="80956" player_name="Tomás Pina" position="Midfielder" position_id="3" x="45.63" y="56.12">
    <Player player_id="55378" player_name="Manu García">3</Player>
    <Player player_id="112994" player_name="Rubén Sobrino">7</Player>
    <Player player_id="168287" player_name="Jonathan Calleri">3</Player>
    <Player player_id="82970" player_name="John Guidetti">1</Player>
    <Player player_id="84471" player_name="Ibai Gómez">2</Player>
    <Player player_id="155335" player_name="Guillermo Maripán">3</Player>
    <Player player_id="126119" player_name="Rubén Duarte">4</Player>
    <Player player_id="92190" player_name="Jony">6</Player>
    <Player player_id="49370" player_name="Víctor Laguardia">1</Player>
  </Player>
  <Player cross_lost="0" cross_success="0" jersey_num="5" pass_lost="12" pass_success="34" player_id="49370" player_name="Víctor Laguardia" position="Defender" position_id="2" x="28.03" y="27.58">
    <Player player_id="112994" player_name="Rubén Sobrino">1</Player>
    <Player player_id="168287" player_name="Jonathan Calleri">5</Player>
    <Player player_id="91406" player_name="Fernando Pacheco">11</Player>
    <Player player_id="90728" player_name="Ximo Navarro">5</Player>
    <Player player_id="126119" player_name="Rubén Duarte">1</Player>
    <Player player_id="155335" player_name="Guillermo Maripán">3</Player>
    <Player player_id="84471" player_name="Ibai Gómez">1</Player>
    <Player player_id="83091" player_name="Borja Bastón">1</Player>
    <Player player_id="92190" player_name="Jony">2</Player>
    <Player player_id="80956" player_name="Tomás Pina">4</Player>
  </Player>
</SoccerFeed>