<?xml version="1.0" encoding="UTF-8"?>
<!-- Copyright 2001-2019 Opta Sportsdata Ltd. All rights reserved. -->
<!-- PRODUCTION HEADER
     produced on:        valde-jobq-a03.nexus.opta.net
     production time:    20190425T144605,695Z
     production module:  Opta::Feed::XML::Soccer::F27
-->
<SoccerFeed act_minute="93" act_period="2" act_second="11" away_team_id="174" away_team_name="Athletic Club" competition_id="23" competition_name="Spanish La Liga" game_date="2019-04-24 19:30:00" game_id="1009650" home_team_id="957" home_team_name="Leganés" season_id="2018" season_name="Season 2018/2019" team_id="957" team_name="Leganés">
  <Player cross_lost="3" cross_success="0" jersey_num="17" pass_lost="9" pass_success="46" player_id="90483" player_name="Javier Eraso" position="Midfielder" position_id="3" x="60.99" y="35.79">
    <Player player_id="161030" player_name="Gerard Gumbau">5</Player>
    <Player player_id="234991" player_name="Youssef En-Nesyri">1</Player>
    <Player player_id="59945" player_name="Rubén Pérez">6</Player>
    <Player player_id="210419" player_name="Rodrigo Tarín">1</Player>
    <Player player_id="47645" player_name="Juanfran">17</Player>
    <Player player_id="68690" player_name="Martin Braithwaite">3</Player>
    <Player player_id="16261" player_name="Iván Cuéllar">1</Player>
    <Player player_id="112540" player_name="Unai Bustinza">3</Player>
    <Player player_id="40380" player_name="Nabil El Zhar">2</Player>
    <Player player_id="112991" player_name="Kenneth Omeruo">3</Player>
    <Player player_id="98914" player_name="Guido Carrillo">3</Player>
  </Player>
  <Player cross_lost="0" cross_success="0" jersey_num="25" pass_lost="0" pass_success="6" player_id="68690" player_name="Martin Braithwaite" position="Substitute" position_id="5" sub_on="68" x="63.45" y="63.52">
    <Player player_id="90483" player_name="Javier Eraso">3</Player>
    <Player player_id="161030" player_name="Gerard Gumbau">2</Player>
    <Player player_id="47645" player_name="Juanfran">1</Player>
  </Player>
  <Player cross_lost="4" cross_success="1" jersey_num="6" pass_lost="14" pass_success="27" player_id="161030" player_name="Gerard Gumbau" position="Midfielder" position_id="3" x="51.02" y="76.49">
    <Player cross="1" player_id="234991" player_name="Youssef En-Nesyri">0</Player>
    <Player player_id="59945" player_name="Rubén Pérez">6</Player>
    <Player player_id="53020" player_name="Dimitrios Siovas">1</Player>
    <Player player_id="210419" player_name="Rodrigo Tarín">1</Player>
    <Player player_id="90483" player_name="Javier Eraso">5</Player>
    <Player player_id="68690" player_name="Martin Braithwaite">1</Player>
    <Player player_id="205606" player_name="Vasyl Kravets">7</Player>
    <Player player_id="40380" player_name="Nabil El Zhar">1</Player>
    <Player player_id="112991" player_name="Kenneth Omeruo">4</Player>
    <Player player_id="98914" player_name="Guido Carrillo">1</Player>
  </Player>
  <Player cross_lost="0" cross_success="0" jersey_num="1" pass_lost="13" pass_success="26" player_id="16261" player_name="Iván Cuéllar" position="Goalkeeper" position_id="1" x="17.01" y="55.56">
    <Player player_id="90483" player_name="Javier Eraso">2</Player>
    <Player player_id="161030" player_name="Gerard Gumbau">1</Player>
    <Player player_id="16261" player_name="Iván Cuéllar">1</Player>
    <Player player_id="234991" player_name="Youssef En-Nesyri">2</Player>
    <Player player_id="112540" player_name="Unai Bustinza">2</Player>
    <Player player_id="205606" player_name="Vasyl Kravets">1</Player>
    <Player player_id="210419" player_name="Rodrigo Tarín">4</Player>
    <Player player_id="47645" player_name="Juanfran">2</Player>
    <Player player_id="112991" player_name="Kenneth Omeruo">6</Player>
    <Player player_id="98914" player_name="Guido Carrillo">5</Player>
  </Player>
  <Player cross_lost="1" cross_success="1" jersey_num="26" pass_lost="6" pass_success="11" player_id="234991" player_name="Youssef En-Nesyri" position="Forward" position_id="4" x="66.11" y="50.30">
    <Player player_id="90483" player_name="Javier Eraso">1</Player>
    <Player player_id="161030" player_name="Gerard Gumbau">2</Player>
    <Player player_id="205606" player_name="Vasyl Kravets">2</Player>
    <Player player_id="112991" player_name="Kenneth Omeruo">1</Player>
    <Player player_id="47645" player_name="Juanfran">1</Player>
    <Player cross="1" player_id="98914" player_name="Guido Carrillo">4</Player>
  </Player>
  <Player cross_lost="0" cross_success="0" jersey_num="21" pass_lost="10" pass_success="50" player_id="59945" player_name="Rubén Pérez" position="Midfielder" position_id="3" x="48.51" y="52.38">
    <Player player_id="161030" player_name="Gerard Gumbau">10</Player>
    <Player player_id="234991" player_name="Youssef En-Nesyri">2</Player>
    <Player player_id="210419" player_name="Rodrigo Tarín">2</Player>
    <Player player_id="47645" player_name="Juanfran">6</Player>
    <Player player_id="90483" player_name="Javier Eraso">10</Player>
    <Player player_id="68690" player_name="Martin Braithwaite">1</Player>
    <Player player_id="16261" player_name="Iván Cuéllar">2</Player>
    <Player player_id="112540" player_name="Unai Bustinza">4</Player>
    <Player player_id="205606" player_name="Vasyl Kravets">2</Player>
    <Player player_id="40380" player_name="Nabil El Zhar">1</Player>
    <Player player_id="112991" player_name="Kenneth Omeruo">7</Player>
    <Player player_id="98914" player_name="Guido Carrillo">3</Player>
  </Player>
  <Player cross_lost="2" cross_success="0" jersey_num="3" pass_lost="11" pass_success="22" player_id="112540" player_name="Unai Bustinza" position="Substitute" position_id="5" sub_on="45" x="51.36" y="29.83">
    <Player player_id="90483" player_name="Javier Eraso">2</Player>
    <Player player_id="59945" player_name="Rubén Pérez">2</Player>
    <Player player_id="205606" player_name="Vasyl Kravets">1</Player>
    <Player player_id="112991" player_name="Kenneth Omeruo">11</Player>
    <Player player_id="47645" player_name="Juanfran">6</Player>
  </Player>
  <Player cross_lost="1" cross_success="1" jersey_num="14" pass_lost="9" pass_success="15" player_id="205606" player_name="Vasyl Kravets" position="Midfielder" position_id="3" sub_off="68" x="42.75" y="84.23">
    <Player player_id="161030" player_name="Gerard Gumbau">3</Player>
    <Player player_id="16261" player_name="Iván Cuéllar">1</Player>
    <Player cross="1" player_id="234991" player_name="Youssef En-Nesyri">1</Player>
    <Player player_id="59945" player_name="Rubén Pérez">4</Player>
    <Player player_id="53020" player_name="Dimitrios Siovas">3</Player>
    <Player player_id="210419" player_name="Rodrigo Tarín">2</Player>
    <Player player_id="98914" player_name="Guido Carrillo">1</Player>
  </Player>
  <Player cross_lost="0" cross_success="1" jersey_num="10" pass_lost="2" pass_success="4" player_id="40380" player_name="Nabil El Zhar" position="Substitute" position_id="5" sub_on="77" x="69.21" y="53.72">
    <Player player_id="90483" player_name="Javier Eraso">1</Player>
    <Player player_id="68690" player_name="Martin Braithwaite">2</Player>
    <Player player_id="47645" player_name="Juanfran">1</Player>
    <Player cross="1" player_id="98914" player_name="Guido Carrillo">0</Player>
  </Player>
  <Player cross_lost="0" cross_success="0" jersey_num="22" pass_lost="6" pass_success="9" player_id="53020" player_name="Dimitrios Siovas" position="Defender" position_id="2" sub_off="45" x="37.03" y="63.38">
    <Player player_id="90483" player_name="Javier Eraso">1</Player>
    <Player player_id="161030" player_name="Gerard Gumbau">1</Player>
    <Player player_id="16261" player_name="Iván Cuéllar">1</Player>
    <Player player_id="234991" player_name="Youssef En-Nesyri">1</Player>
    <Player player_id="59945" player_name="Rubén Pérez">1</Player>
    <Player player_id="210419" player_name="Rodrigo Tarín">1</Player>
    <Player player_id="112991" player_name="Kenneth Omeruo">2</Player>
    <Player player_id="98914" player_name="Guido Carrillo">1</Player>
  </Player>
  <Player cross_lost="1" cross_success="0" jersey_num="15" pass_lost="8" pass_success="21" player_id="210419" player_name="Rodrigo Tarín" position="Defender" position_id="2" sub_off="77" x="38.54" y="44.69">
    <Player player_id="90483" player_name="Javier Eraso">2</Player>
    <Player player_id="161030" player_name="Gerard Gumbau">1</Player>
    <Player player_id="16261" player_name="Iván Cuéllar">2</Player>
    <Player player_id="59945" player_name="Rubén Pérez">4</Player>
    <Player player_id="205606" player_name="Vasyl Kravets">1</Player>
    <Player player_id="47645" player_name="Juanfran">1</Player>
    <Player player_id="112991" player_name="Kenneth Omeruo">9</Player>
    <Player player_id="98914" player_name="Guido Carrillo">1</Player>
  </Player>
  <Player cross_lost="8" cross_success="3" jersey_num="2" pass_lost="11" pass_success="38" player_id="47645" player_name="Juanfran" position="Midfielder" position_id="3" x="60.74" y="11.19">
    <Player player_id="90483" player_name="Javier Eraso">14</Player>
    <Player cross="1" player_id="68690" player_name="Martin Braithwaite">0</Player>
    <Player cross="1" player_id="234991" player_name="Youssef En-Nesyri">5</Player>
    <Player player_id="59945" player_name="Rubén Pérez">1</Player>
    <Player player_id="112540" player_name="Unai Bustinza">7</Player>
    <Player player_id="40380" player_name="Nabil El Zhar">2</Player>
    <Player player_id="210419" player_name="Rodrigo Tarín">4</Player>
    <Player player_id="112991" player_name="Kenneth Omeruo">2</Player>
    <Player cross="1" player_id="98914" player_name="Guido Carrillo">3</Player>
  </Player>
  <Player cross_lost="0" cross_success="0" jersey_num="24" pass_lost="12" pass_success="61" player_id="112991" player_name="Kenneth Omeruo" position="Defender" position_id="2" x="37.41" y="52.60">
    <Player player_id="161030" player_name="Gerard Gumbau">7</Player>
    <Player player_id="234991" player_name="Youssef En-Nesyri">2</Player>
    <Player player_id="59945" player_name="Rubén Pérez">9</Player>
    <Player player_id="210419" player_name="Rodrigo Tarín">4</Player>
    <Player player_id="47645" player_name="Juanfran">9</Player>
    <Player player_id="90483" player_name="Javier Eraso">4</Player>
    <Player player_id="68690" player_name="Martin Braithwaite">1</Player>
    <Player player_id="16261" player_name="Iván Cuéllar">10</Player>
    <Player player_id="112540" player_name="Unai Bustinza">9</Player>
    <Player player_id="205606" player_name="Vasyl Kravets">1</Player>
    <Player player_id="40380" player_name="Nabil El Zhar">2</Player>
    <Player player_id="98914" player_name="Guido Carrillo">3</Player>
  </Player>
  <Player cross_lost="0" cross_success="0" jersey_num="9" pass_lost="13" pass_success="15" player_id="98914" player_name="Guido Carrillo" position="Forward" position_id="4" x="66.93" y="47.24">
    <Player player_id="90483" player_name="Javier Eraso">2</Player>
    <Player player_id="161030" player_name="Gerard Gumbau">2</Player>
    <Player player_id="234991" player_name="Youssef En-Nesyri">3</Player>
    <Player player_id="59945" player_name="Rubén Pérez">3</Player>
    <Player player_id="112540" player_name="Unai Bustinza">1</Player>
    <Player player_id="205606" player_name="Vasyl Kravets">1</Player>
    <Player player_id="47645" player_name="Juanfran">3</Player>
  </Player>
</SoccerFeed>