<?xml version="1.0" encoding="UTF-8"?>
<!-- Copyright 2001-2019 Opta Sportsdata Ltd. All rights reserved. -->
<!-- PRODUCTION HEADER
     produced on:        valde-jobq-a04.nexus.opta.net
     production time:    20190424T192603,334Z
     production module:  Opta::Feed::XML::Soccer::F27
-->
<SoccerFeed act_minute="96" act_period="2" act_second="18" away_team_id="2893" away_team_name="Girona" competition_id="23" competition_name="Spanish La Liga" game_date="2019-04-23 19:30:00" game_id="1009654" home_team_id="192" home_team_name="Real Valladolid" season_id="2018" season_name="Season 2018/2019" team_id="2893" team_name="Girona">
  <Player cross_lost="0" cross_success="0" jersey_num="12" pass_lost="7" pass_success="21" player_id="230046" player_name="Douglas Luiz" position="Substitute" position_id="5" sub_on="64" x="49.69" y="52.76">
    <Player player_id="55317" player_name="Bernardo Espinosa">1</Player>
    <Player player_id="120026" player_name="Yassine Bounou">1</Player>
    <Player player_id="63119" player_name="Juanpe">4</Player>
    <Player player_id="52117" player_name="Seydou Doumbia">2</Player>
    <Player player_id="131411" player_name="Pere Pons">4</Player>
    <Player player_id="139472" player_name="Álex Granell">3</Player>
    <Player player_id="88550" player_name="Portu">1</Player>
    <Player player_id="63904" player_name="Borja García">1</Player>
    <Player player_id="80077" player_name="Jonás Ramalho">3</Player>
    <Player player_id="61595" player_name="Marc Muniesa">1</Player>
  </Player>
  <Player cross_lost="0" cross_success="0" jersey_num="2" pass_lost="10" pass_success="35" player_id="55317" player_name="Bernardo Espinosa" position="Defender" position_id="2" x="36.70" y="51.24">
    <Player player_id="230046" player_name="Douglas Luiz">1</Player>
    <Player player_id="63119" player_name="Juanpe">12</Player>
    <Player player_id="80908" player_name="Raúl García">2</Player>
    <Player player_id="131411" player_name="Pere Pons">3</Player>
    <Player player_id="139472" player_name="Álex Granell">4</Player>
    <Player player_id="80077" player_name="Jonás Ramalho">1</Player>
    <Player player_id="61595" player_name="Marc Muniesa">12</Player>
  </Player>
  <Player cross_lost="0" cross_success="0" jersey_num="24" pass_lost="0" pass_success="2" player_id="441164" player_name="Pedro Porro" position="Substitute" position_id="5" sub_on="87" x="65.62" y="8.85">
    <Player player_id="80077" player_name="Jonás Ramalho">1</Player>
    <Player player_id="88550" player_name="Portu">1</Player>
  </Player>
  <Player cross_lost="0" cross_success="0" jersey_num="13" pass_lost="10" pass_success="25" player_id="120026" player_name="Yassine Bounou" position="Goalkeeper" position_id="1" x="10.49" y="50.99">
    <Player player_id="55317" player_name="Bernardo Espinosa">2</Player>
    <Player player_id="230046" player_name="Douglas Luiz">3</Player>
    <Player player_id="63119" player_name="Juanpe">5</Player>
    <Player player_id="131411" player_name="Pere Pons">1</Player>
    <Player player_id="139472" player_name="Álex Granell">2</Player>
    <Player player_id="80077" player_name="Jonás Ramalho">2</Player>
    <Player player_id="61595" player_name="Marc Muniesa">5</Player>
    <Player player_id="49464" player_name="Cristhian Stuani">5</Player>
  </Player>
  <Player cross_lost="1" cross_success="0" jersey_num="15" pass_lost="11" pass_success="44" player_id="63119" player_name="Juanpe" position="Defender" position_id="2" x="41.01" y="34.40">
    <Player player_id="55317" player_name="Bernardo Espinosa">10</Player>
    <Player player_id="120026" player_name="Yassine Bounou">2</Player>
    <Player player_id="139472" player_name="Álex Granell">4</Player>
    <Player player_id="131411" player_name="Pere Pons">7</Player>
    <Player player_id="63904" player_name="Borja García">5</Player>
    <Player player_id="230046" player_name="Douglas Luiz">5</Player>
    <Player player_id="88550" player_name="Portu">2</Player>
    <Player player_id="80077" player_name="Jonás Ramalho">5</Player>
    <Player player_id="61595" player_name="Marc Muniesa">1</Player>
    <Player player_id="49464" player_name="Cristhian Stuani">3</Player>
  </Player>
  <Player cross_lost="5" cross_success="0" jersey_num="14" pass_lost="6" pass_success="16" player_id="80908" player_name="Raúl García" position="Midfielder" position_id="3" sub_off="64" x="44.20" y="90.80">
    <Player player_id="55317" player_name="Bernardo Espinosa">1</Player>
    <Player player_id="139472" player_name="Álex Granell">3</Player>
    <Player player_id="63904" player_name="Borja García">7</Player>
    <Player player_id="61595" player_name="Marc Muniesa">3</Player>
    <Player player_id="49464" player_name="Cristhian Stuani">2</Player>
  </Player>
  <Player cross_lost="0" cross_success="0" jersey_num="22" pass_lost="0" pass_success="2" player_id="52117" player_name="Seydou Doumbia" position="Substitute" position_id="5" sub_on="76" x="76.16" y="66.84">
    <Player player_id="441164" player_name="Pedro Porro">1</Player>
    <Player player_id="131411" player_name="Pere Pons">1</Player>
  </Player>
  <Player cross_lost="1" cross_success="0" jersey_num="8" pass_lost="4" pass_success="29" player_id="131411" player_name="Pere Pons" position="Midfielder" position_id="3" sub_off="87" x="55.40" y="37.95">
    <Player player_id="55317" player_name="Bernardo Espinosa">3</Player>
    <Player player_id="120026" player_name="Yassine Bounou">1</Player>
    <Player player_id="139472" player_name="Álex Granell">6</Player>
    <Player player_id="63904" player_name="Borja García">3</Player>
    <Player player_id="63119" player_name="Juanpe">6</Player>
    <Player player_id="52117" player_name="Seydou Doumbia">1</Player>
    <Player player_id="88550" player_name="Portu">2</Player>
    <Player player_id="80077" player_name="Jonás Ramalho">3</Player>
    <Player player_id="61595" player_name="Marc Muniesa">3</Player>
    <Player player_id="49464" player_name="Cristhian Stuani">1</Player>
  </Player>
  <Player cross_lost="8" cross_success="4" jersey_num="6" pass_lost="9" pass_success="39" player_id="139472" player_name="Álex Granell" position="Midfielder" position_id="3" x="52.01" y="71.34">
    <Player player_id="55317" player_name="Bernardo Espinosa">1</Player>
    <Player cross="1" player_id="120026" player_name="Yassine Bounou">1</Player>
    <Player player_id="80908" player_name="Raúl García">9</Player>
    <Player player_id="131411" player_name="Pere Pons">1</Player>
    <Player player_id="63904" player_name="Borja García">14</Player>
    <Player player_id="230046" player_name="Douglas Luiz">3</Player>
    <Player player_id="63119" player_name="Juanpe">1</Player>
    <Player cross="2" player_id="88550" player_name="Portu">2</Player>
    <Player player_id="80077" player_name="Jonás Ramalho">4</Player>
    <Player player_id="61595" player_name="Marc Muniesa">3</Player>
    <Player cross="1" player_id="49464" player_name="Cristhian Stuani">0</Player>
  </Player>
  <Player cross_lost="1" cross_success="0" jersey_num="9" pass_lost="6" pass_success="14" player_id="88550" player_name="Portu" position="Forward" position_id="4" x="58.74" y="37.82">
    <Player player_id="230046" player_name="Douglas Luiz">1</Player>
    <Player player_id="63119" player_name="Juanpe">2</Player>
    <Player player_id="80908" player_name="Raúl García">1</Player>
    <Player player_id="131411" player_name="Pere Pons">3</Player>
    <Player player_id="63904" player_name="Borja García">3</Player>
    <Player player_id="80077" player_name="Jonás Ramalho">3</Player>
    <Player player_id="49464" player_name="Cristhian Stuani">1</Player>
  </Player>
  <Player cross_lost="3" cross_success="1" jersey_num="10" pass_lost="8" pass_success="34" player_id="63904" player_name="Borja García" position="Forward" position_id="4" x="53.75" y="78.96">
    <Player player_id="55317" player_name="Bernardo Espinosa">2</Player>
    <Player player_id="80908" player_name="Raúl García">6</Player>
    <Player player_id="131411" player_name="Pere Pons">2</Player>
    <Player player_id="139472" player_name="Álex Granell">12</Player>
    <Player player_id="230046" player_name="Douglas Luiz">2</Player>
    <Player player_id="63119" player_name="Juanpe">1</Player>
    <Player player_id="52117" player_name="Seydou Doumbia">2</Player>
    <Player player_id="88550" player_name="Portu">4</Player>
    <Player player_id="61595" player_name="Marc Muniesa">2</Player>
    <Player cross="1" player_id="49464" player_name="Cristhian Stuani">1</Player>
  </Player>
  <Player cross_lost="3" cross_success="0" jersey_num="4" pass_lost="5" pass_success="17" player_id="80077" player_name="Jonás Ramalho" position="Midfielder" position_id="3" x="51.55" y="16.63">
    <Player player_id="55317" player_name="Bernardo Espinosa">2</Player>
    <Player player_id="230046" player_name="Douglas Luiz">3</Player>
    <Player player_id="441164" player_name="Pedro Porro">1</Player>
    <Player player_id="63119" player_name="Juanpe">5</Player>
    <Player player_id="139472" player_name="Álex Granell">2</Player>
    <Player player_id="131411" player_name="Pere Pons">2</Player>
    <Player player_id="88550" player_name="Portu">1</Player>
    <Player player_id="63904" player_name="Borja García">1</Player>
  </Player>
  <Player cross_lost="0" cross_success="0" jersey_num="20" pass_lost="2" pass_success="41" player_id="61595" player_name="Marc Muniesa" position="Defender" position_id="2" sub_off="76" x="33.09" y="77.76">
    <Player player_id="55317" player_name="Bernardo Espinosa">10</Player>
    <Player player_id="120026" player_name="Yassine Bounou">2</Player>
    <Player player_id="80908" player_name="Raúl García">7</Player>
    <Player player_id="131411" player_name="Pere Pons">3</Player>
    <Player player_id="139472" player_name="Álex Granell">8</Player>
    <Player player_id="63904" player_name="Borja García">7</Player>
    <Player player_id="230046" player_name="Douglas Luiz">1</Player>
    <Player player_id="63119" player_name="Juanpe">1</Player>
    <Player player_id="88550" player_name="Portu">1</Player>
    <Player player_id="80077" player_name="Jonás Ramalho">1</Player>
  </Player>
  <Player cross_lost="0" cross_success="0" jersey_num="7" pass_lost="8" pass_success="9" player_id="49464" player_name="Cristhian Stuani" position="Forward" position_id="4" x="59.12" y="57.70">
    <Player player_id="80908" player_name="Raúl García">1</Player>
    <Player player_id="131411" player_name="Pere Pons">2</Player>
    <Player player_id="139472" player_name="Álex Granell">1</Player>
    <Player player_id="88550" player_name="Portu">2</Player>
    <Player player_id="63904" player_name="Borja García">2</Player>
    <Player player_id="61595" player_name="Marc Muniesa">1</Player>
  </Player>
</SoccerFeed>