<?xml version="1.0" encoding="UTF-8"?>
<!-- Copyright 2001-2019 Opta Sportsdata Ltd. All rights reserved. -->
<!-- PRODUCTION HEADER
     produced on:        valde-jobq-a04.nexus.opta.net
     production time:    20190115T174622,618Z
     production module:  Opta::Feed::XML::Soccer::F28
-->
<Possession away_team_id="2894" away_team_name="Huesca" competition_id="23" competition_name="Spanish La Liga" date="20190112T120000+0000" game_id="1009505" home_team_id="957" home_team_name="Leganés" match_time="97" period="2" season_id="2018" season_name="Season 2018/2019" timestamp="20190115T174621+0000">
  <PossessionWave Type="BallPossession">
    <Intervals>
      <IntervalLength Type="5">
        <Interval Type="0-5">
          <Away>54.3</Away>
          <Home>45.7</Home>
        </Interval>
        <Interval Type="6-10">
          <Away>67.3</Away>
          <Home>32.7</Home>
        </Interval>
        <Interval Type="11-15">
          <Away>39.5</Away>
          <Home>60.5</Home>
        </Interval>
        <Interval Type="16-20">
          <Away>46.2</Away>
          <Home>53.8</Home>
        </Interval>
        <Interval Type="21-25">
          <Away>43.8</Away>
          <Home>56.2</Home>
        </Interval>
        <Interval Type="26-30">
          <Away>62.9</Away>
          <Home>37.1</Home>
        </Interval>
        <Interval Type="31-35">
          <Away>46.8</Away>
          <Home>53.2</Home>
        </Interval>
        <Interval Type="36-40">
          <Away>34.5</Away>
          <Home>65.5</Home>
        </Interval>
        <Interval Type="41-45">
          <Away>54.8</Away>
          <Home>45.2</Home>
        </Interval>
        <Interval Type="46-50">
          <Away>60.0</Away>
          <Home>40.0</Home>
        </Interval>
        <Interval Type="51-55">
          <Away>38.3</Away>
          <Home>61.7</Home>
        </Interval>
        <Interval Type="56-60">
          <Away>17.9</Away>
          <Home>82.1</Home>
        </Interval>
        <Interval Type="61-65">
          <Away>13.6</Away>
          <Home>86.4</Home>
        </Interval>
        <Interval Type="66-70">
          <Away>83.3</Away>
          <Home>16.7</Home>
        </Interval>
        <Interval Type="71-75">
          <Away>46.8</Away>
          <Home>53.2</Home>
        </Interval>
        <Interval Type="76-80">
          <Away>68.4</Away>
          <Home>31.6</Home>
        </Interval>
        <Interval Type="81-85">
          <Away>52.0</Away>
          <Home>48.0</Home>
        </Interval>
        <Interval Type="86-90">
          <Away>53.7</Away>
          <Home>46.3</Home>
        </Interval>
      </IntervalLength>
      <IntervalLength Type="15">
        <Interval Type="0-15">
          <Away>55.4</Away>
          <Home>44.6</Home>
        </Interval>
        <Interval Type="16-30">
          <Away>52.9</Away>
          <Home>47.1</Home>
        </Interval>
        <Interval Type="31-45">
          <Away>48.2</Away>
          <Home>51.8</Home>
        </Interval>
        <Interval Type="46-60">
          <Away>41.8</Away>
          <Home>58.2</Home>
        </Interval>
        <Interval Type="61-75">
          <Away>46.1</Away>
          <Home>53.9</Home>
        </Interval>
        <Interval Type="76-90">
          <Away>57.0</Away>
          <Home>43.0</Home>
        </Interval>
      </IntervalLength>
      <IntervalLength Type="45">
        <Interval Type="0-45">
          <Away>51.9</Away>
          <Home>48.1</Home>
        </Interval>
        <Interval Type="46-90">
          <Away>48.8</Away>
          <Home>51.2</Home>
        </Interval>
      </IntervalLength>
    </Intervals>
    <LastX>
      <Last Type="5">
        <Away>52.6</Away>
        <Home>47.4</Home>
      </Last>
      <Last Type="10">
        <Away>53.8</Away>
        <Home>46.2</Home>
      </Last>
      <Last Type="15">
        <Away>53.1</Away>
        <Home>46.9</Home>
      </Last>
      <Last Type="20">
        <Away>55.1</Away>
        <Home>44.9</Home>
      </Last>
      <Last Type="25">
        <Away>55.9</Away>
        <Home>44.1</Home>
      </Last>
      <Last Type="30">
        <Away>54.6</Away>
        <Home>45.4</Home>
      </Last>
    </LastX>
    <Overall>
      <Away>50.4</Away>
      <Home>49.6</Home>
    </Overall>
  </PossessionWave>
  <PossessionWave Type="Territorial">
    <Intervals>
      <IntervalLength Type="5">
        <Interval Type="0-5">
          <Away>50.0</Away>
          <Home>50.0</Home>
        </Interval>
        <Interval Type="6-10">
          <Away>61.8</Away>
          <Home>38.2</Home>
        </Interval>
        <Interval Type="11-15">
          <Away>36.8</Away>
          <Home>63.2</Home>
        </Interval>
        <Interval Type="16-20">
          <Away>38.5</Away>
          <Home>61.5</Home>
        </Interval>
        <Interval Type="21-25">
          <Away>56.2</Away>
          <Home>43.8</Home>
        </Interval>
        <Interval Type="26-30">
          <Away>59.7</Away>
          <Home>40.3</Home>
        </Interval>
        <Interval Type="31-35">
          <Away>38.7</Away>
          <Home>61.3</Home>
        </Interval>
        <Interval Type="36-40">
          <Away>44.8</Away>
          <Home>55.2</Home>
        </Interval>
        <Interval Type="41-45">
          <Away>38.4</Away>
          <Home>61.6</Home>
        </Interval>
        <Interval Type="46-50">
          <Away>43.3</Away>
          <Home>56.7</Home>
        </Interval>
        <Interval Type="51-55">
          <Away>36.2</Away>
          <Home>63.8</Home>
        </Interval>
        <Interval Type="56-60">
          <Away>33.3</Away>
          <Home>66.7</Home>
        </Interval>
        <Interval Type="61-65">
          <Away>45.5</Away>
          <Home>54.5</Home>
        </Interval>
        <Interval Type="66-70">
          <Away>38.9</Away>
          <Home>61.1</Home>
        </Interval>
        <Interval Type="71-75">
          <Away>45.2</Away>
          <Home>54.8</Home>
        </Interval>
        <Interval Type="76-80">
          <Away>60.5</Away>
          <Home>39.5</Home>
        </Interval>
        <Interval Type="81-85">
          <Away>44.0</Away>
          <Home>56.0</Home>
        </Interval>
        <Interval Type="86-90">
          <Away>44.2</Away>
          <Home>55.8</Home>
        </Interval>
      </IntervalLength>
      <IntervalLength Type="15">
        <Interval Type="0-15">
          <Away>51.1</Away>
          <Home>48.9</Home>
        </Interval>
        <Interval Type="16-30">
          <Away>54.4</Away>
          <Home>45.6</Home>
        </Interval>
        <Interval Type="31-45">
          <Away>39.6</Away>
          <Home>60.4</Home>
        </Interval>
        <Interval Type="46-60">
          <Away>38.4</Away>
          <Home>61.6</Home>
        </Interval>
        <Interval Type="61-75">
          <Away>44.1</Away>
          <Home>55.9</Home>
        </Interval>
        <Interval Type="76-90">
          <Away>48.1</Away>
          <Home>51.9</Home>
        </Interval>
      </IntervalLength>
      <IntervalLength Type="45">
        <Interval Type="0-45">
          <Away>47.8</Away>
          <Home>52.2</Home>
        </Interval>
        <Interval Type="46-90">
          <Away>43.6</Away>
          <Home>56.4</Home>
        </Interval>
      </IntervalLength>
    </Intervals>
    <LastX>
      <Last Type="5">
        <Away>50.0</Away>
        <Home>50.0</Home>
      </Last>
      <Last Type="10">
        <Away>48.7</Away>
        <Home>51.3</Home>
      </Last>
      <Last Type="15">
        <Away>42.5</Away>
        <Home>57.5</Home>
      </Last>
      <Last Type="20">
        <Away>49.0</Away>
        <Home>51.0</Home>
      </Last>
      <Last Type="25">
        <Away>48.5</Away>
        <Home>51.5</Home>
      </Last>
      <Last Type="30">
        <Away>47.1</Away>
        <Home>52.9</Home>
      </Last>
    </LastX>
    <Overall>
      <Away>45.8</Away>
      <Home>54.2</Home>
    </Overall>
  </PossessionWave>
  <PossessionWave Type="TerritorialThird">
    <Intervals>
      <IntervalLength Type="5">
        <Interval Type="0-5">
          <Away>15.2</Away>
          <Home>21.7</Home>
          <Middle>63.1</Middle>
        </Interval>
        <Interval Type="6-10">
          <Away>16.4</Away>
          <Home>34.5</Home>
          <Middle>49.1</Middle>
        </Interval>
        <Interval Type="11-15">
          <Away>21.1</Away>
          <Home>7.9</Home>
          <Middle>71.0</Middle>
        </Interval>
        <Interval Type="16-20">
          <Away>38.5</Away>
          <Home>15.4</Home>
          <Middle>46.1</Middle>
        </Interval>
        <Interval Type="21-25">
          <Away>29.2</Away>
          <Home>31.2</Home>
          <Middle>39.6</Middle>
        </Interval>
        <Interval Type="26-30">
          <Away>16.1</Away>
          <Home>33.9</Home>
          <Middle>50.0</Middle>
        </Interval>
        <Interval Type="31-35">
          <Away>24.2</Away>
          <Home>4.8</Home>
          <Middle>71.0</Middle>
        </Interval>
        <Interval Type="36-40">
          <Away>31.0</Away>
          <Home>24.1</Home>
          <Middle>44.9</Middle>
        </Interval>
        <Interval Type="41-45">
          <Away>20.5</Away>
          <Home>17.8</Home>
          <Middle>61.7</Middle>
        </Interval>
        <Interval Type="46-50">
          <Away>30.0</Away>
          <Home>20.0</Home>
          <Middle>50.0</Middle>
        </Interval>
        <Interval Type="51-55">
          <Away>10.6</Away>
          <Home>21.3</Home>
          <Middle>68.1</Middle>
        </Interval>
        <Interval Type="56-60">
          <Away>28.2</Away>
          <Home>12.8</Home>
          <Middle>59.0</Middle>
        </Interval>
        <Interval Type="61-65">
          <Away>13.6</Away>
          <Home>22.7</Home>
          <Middle>63.7</Middle>
        </Interval>
        <Interval Type="66-70">
          <Away>33.3</Away>
          <Home>16.7</Home>
          <Middle>50.0</Middle>
        </Interval>
        <Interval Type="71-75">
          <Away>27.4</Away>
          <Home>16.1</Home>
          <Middle>56.5</Middle>
        </Interval>
        <Interval Type="76-80">
          <Away>10.5</Away>
          <Home>31.6</Home>
          <Middle>57.9</Middle>
        </Interval>
        <Interval Type="81-85">
          <Away>32.0</Away>
          <Home>24.0</Home>
          <Middle>44.0</Middle>
        </Interval>
        <Interval Type="86-90">
          <Away>22.1</Away>
          <Home>24.2</Home>
          <Middle>53.7</Middle>
        </Interval>
      </IntervalLength>
      <IntervalLength Type="15">
        <Interval Type="0-15">
          <Away>17.3</Away>
          <Home>23.0</Home>
          <Middle>59.7</Middle>
        </Interval>
        <Interval Type="16-30">
          <Away>25.0</Away>
          <Home>29.4</Home>
          <Middle>45.6</Middle>
        </Interval>
        <Interval Type="31-45">
          <Away>23.8</Away>
          <Home>14.0</Home>
          <Middle>62.2</Middle>
        </Interval>
        <Interval Type="46-60">
          <Away>23.3</Away>
          <Home>18.5</Home>
          <Middle>58.2</Middle>
        </Interval>
        <Interval Type="61-75">
          <Away>25.5</Away>
          <Home>17.6</Home>
          <Middle>56.9</Middle>
        </Interval>
        <Interval Type="76-90">
          <Away>20.9</Away>
          <Home>25.9</Home>
          <Middle>53.2</Middle>
        </Interval>
      </IntervalLength>
      <IntervalLength Type="45">
        <Interval Type="0-45">
          <Away>22.1</Away>
          <Home>21.6</Home>
          <Middle>56.3</Middle>
        </Interval>
        <Interval Type="46-90">
          <Away>22.9</Away>
          <Home>21.2</Home>
          <Middle>55.9</Middle>
        </Interval>
      </IntervalLength>
    </Intervals>
    <Overall>
      <Away>22.5</Away>
      <Home>21.4</Home>
      <Middle>56.1</Middle>
    </Overall>
  </PossessionWave>
</Possession>